pychatworkAPI/__init__.py
pychatworkAPI/api.py
pychatworkAPI-1.13.dist-info/LICENSE
pychatworkAPI-1.13.dist-info/METADATA
pychatworkAPI-1.13.dist-info/WHEEL
pychatworkAPI-1.13.dist-info/top_level.txt
pychatworkAPI-1.13.dist-info/RECORD
