Metadata-Version: 2.1
Name: pychatworkAPI
Version: 1.13
Summary: pychatworkAPI is a python package to access chatwork offline.
Home-page: https://github.com/dc-aichara/pyChatwork
Author: Dayal Chand Aichara
Author-email: dc.aichara@gmail.com
License: MIT
Download-URL: https://github.com/dc-aichara/pychatworkAPI/archive/V-1.13.tar.gz
Keywords: chatwork,chatwork-api
Platform: UNKNOWN
Classifier: Development Status :: 5 - Production/Stable
Classifier: Intended Audience :: Developers
Classifier: Topic :: Software Development :: Build Tools
Classifier: License :: OSI Approved :: MIT License
Classifier: Programming Language :: Python :: 3
Classifier: Programming Language :: Python :: 3.5
Classifier: Programming Language :: Python :: 3.6
Classifier: Programming Language :: Python :: 3.7
Classifier: Operating System :: OS Independent
Requires-Dist: requests
